pilotspace/__init__.py
pilotspace/py.typed
pilotspace-0.1.0.dist-info/METADATA
pilotspace-0.1.0.dist-info/WHEEL
pilotspace-0.1.0.dist-info/licenses/LICENSE
pilotspace-0.1.0.dist-info/RECORD
