Metadata-Version: 2.4
Name: pilotspace
Version: 0.1.0
Summary: The AI-Native Workspace Revolution.
Author-email: LIghtJUNction <lightjunction.me@gmail.com>
License-File: LICENSE
Requires-Python: >=3.14
